py_pgp-0.0.1.dist-info/RECORD
py_pgp-0.0.1.dist-info/top_level.txt
py_pgp-0.0.1.dist-info/METADATA
py_pgp-0.0.1.dist-info/entry_points.txt
py_pgp-0.0.1.dist-info/WHEEL
py_pgp-0.0.1.dist-info/DESCRIPTION.rst
py_pgp-0.0.1.dist-info/metadata.json
pgp/signature.py
pgp/utils.py
pgp/compat.py
pgp/interfaces.py
pgp/__init__.py
pgp/detached_signature.py
pgp/signature_verification.py
pgp/context_managers.py
pgp/test_keys.py
pgp/user_id.py
pgp/py3.py
pgp/message.py
pgp/merge.py
pgp/exceptions.py
pgp/parse.py
pgp/s2k.py
pgp/crc24.py
pgp/py2.py
pgp/armor.py
pgp/transferrable_keys.py
pgp/regex.py
pgp/shortcuts.py
pgp/pinentry/__init__.py
pgp/pinentry/getpass.py
pgp/pinentry/gpg_agent.py
pgp/keyserver/hkp.py
pgp/keyserver/__init__.py
pgp/cipher/wrapper.py
pgp/cipher/base.py
pgp/cipher/__init__.py
pgp/cipher/aidea.py
pgp/cipher/camellia.py
pgp/cipher/twofish.py
pgp/cipher/tests/test_camellia.py
pgp/cipher/tests/__init__.py
pgp/cipher/tests/test_twofish.py
pgp/cipher/tests/test_aidea.py
pgp/db/__init__.py
pgp/db/gpg.py
pgp/packets/user_attribute_subpackets.py
pgp/packets/__init__.py
pgp/packets/constants.py
pgp/packets/signature_subpackets.py
pgp/packets/packets.py
pgp/packets/parsers.py
pgp/packets/tests/__init__.py
pgp/commands/__init__.py
pgp/commands/gpg/store.py
pgp/commands/gpg/edit_key.py
pgp/commands/gpg/dearmor.py
pgp/commands/gpg/export_secret_subkeys.py
pgp/commands/gpg/list_packets.py
pgp/commands/gpg/clearsign.py
pgp/commands/gpg/io_helper.py
pgp/commands/gpg/delete_secret_and_public_key.py
pgp/commands/gpg/desig_revoke.py
pgp/commands/gpg/update_trustdb.py
pgp/commands/gpg/export_ownertrust.py
pgp/commands/gpg/encrypt.py
pgp/commands/gpg/export.py
pgp/commands/gpg/__init__.py
pgp/commands/gpg/sign.py
pgp/commands/gpg/send_keys.py
pgp/commands/gpg/fingerprint.py
pgp/commands/gpg/delete_secret_key.py
pgp/commands/gpg/fetch_keys.py
pgp/commands/gpg/trustdb_helper.py
pgp/commands/gpg/verification_helper.py
pgp/commands/gpg/import_keys.py
pgp/commands/gpg/decrypt.py
pgp/commands/gpg/message_.py
pgp/commands/gpg/list_.py
pgp/commands/gpg/delete_key.py
pgp/commands/gpg/lsign_key.py
pgp/commands/gpg/recv_keys.py
