Metadata-Version: 2.0
Name: py-pgp
Version: 0.0.1
Summary: A Python implementation of OpenPGP
Home-page: https://github.com/mitchellrj/python-pgp
Author: Richard Mitchell
Author-email: mitch@awesomeco.de
License: GPL 3
Keywords: pgp openpgp gpg cryptography security privacy
Platform: UNKNOWN
Classifier: Development Status :: 2 - Pre-Alpha
Classifier: Intended Audience :: Developers
Classifier: License :: OSI Approved :: GNU General Public License v3 or later (GPLv3+)
Classifier: Programming Language :: Python :: 2.7
Classifier: Programming Language :: Python :: 3.3
Classifier: Programming Language :: Python :: 3.4
Classifier: Programming Language :: Python :: Implementation :: CPython
Classifier: Programming Language :: Python :: Implementation :: PyPy
Classifier: Topic :: Security :: Cryptography
Requires-Dist: python-magic
Requires-Dist: pycrypto
Requires-Dist: six
Requires-Dist: requests
Requires-Dist: zope.interface
Requires-Dist: pgpdump3
Provides-Extra: camellia
Requires-Dist: camcrypt; extra == 'camellia'
Provides-Extra: dev
Requires-Dist: Sphinx; extra == 'dev'
Requires-Dist: coverage; extra == 'dev'
Requires-Dist: nose; extra == 'dev'
Requires-Dist: tissue; extra == 'dev'
Provides-Extra: docs
Requires-Dist: Sphinx; extra == 'docs'
Provides-Extra: integration
Requires-Dist: python-coveralls; extra == 'integration'
Requires-Dist: coverage; extra == 'integration'
Requires-Dist: nose; extra == 'integration'
Requires-Dist: tissue; extra == 'integration'
Provides-Extra: test
Requires-Dist: coverage; extra == 'test'
Requires-Dist: nose; extra == 'test'
Requires-Dist: tissue; extra == 'test'
Provides-Extra: twofish
Requires-Dist: twofish; extra == 'twofish'
